pyNukiBT/__init__.py
pyNukiBT/const.py
pyNukiBT/nuki.py
pynukibt-0.0.19.dist-info/licenses/LICENSE
pynukibt-0.0.19.dist-info/METADATA
pynukibt-0.0.19.dist-info/WHEEL
pynukibt-0.0.19.dist-info/top_level.txt
pynukibt-0.0.19.dist-info/RECORD
