Metadata-Version: 2.4
Name: pyNukiBT
Version: 0.0.19
Summary: Nuki Bluetooth API
Author-email: Ronen Gruengras <ronengr@gmail.com>
Project-URL: Homepage, https://github.com/ronengr/pyNukiBT
Project-URL: Bug Tracker, https://github.com/ronengr/pyNukiBT/issues
Classifier: Programming Language :: Python :: 3
Classifier: License :: OSI Approved :: MIT License
Classifier: Operating System :: OS Independent
Requires-Python: >=3.7
License-File: LICENSE
Requires-Dist: bleak>=0.20
Requires-Dist: crccheck>=1.3.0
Requires-Dist: PyNaCl>=1.3.0
Requires-Dist: construct>=2.10.70
Requires-Dist: packaging>=23.1
Dynamic: license-file
